{
  "speaker": "",
  "reference": "Chapter 5, Verse 5.5",
  "sanskrit": "",
  "meanings": {
    "english": "Dedication and devotion can lead to spiritual growth, just like renunciation. Those who see the value in both paths truly understand the truth.",
    "hindi": "समर्पण और भक्ति आत्मिक विकास के लिए नेतृत्व कर सकते हैं, जैसे कि त्याग। जो लोग दोनों मार्गों में मूल्य देखते हैं वे सच्चाई को वास्तव में समझते हैं।",
    "gujarati": "સમર્પણ અને ભક્તિ આધ્યાત્મિક વૃદ્ધિ તરફ દોરી શકે છે, ત્યાં સંયમ પણ. જે બંને માર્ગોમાં મૂલ્ય જોઈ શકે છે, તેઓ જ સત્યને સાચે જ સમજે છે.",
    "tamil": "அர்ப்பணிப்பும் பக்தியும் துறவு போலவே ஆன்மீக வளர்ச்சிக்கு வழிவகுக்கின்றன. இரு பாதைகளின் மதிப்பையும் பார்ப்பவர்கள் உண்மையை உணர்ந்து கொள்கிறார்கள்.",
    "telugu": "నిష్ఠ, భక్తి కూడా త్యాగం వలె ఆధ్యాత్మిక వృద్ధికి దారితీస్తాయి. రెండు మార్గాలలోనూ విలువను గ్రహించేవారు నిజమైన సత్యాన్ని అర్థం చేసుకుంటారు.",
    "kannada": "ಸಮರ್ಪಣೆ ಮತ್ತು ಭಕ್ತಿಯು ತ್ಯಾಗದಂತೆಯೇ ಆಧ್ಯಾತ್ಮಿಕ ಬೆಳವಣಿಗೆಗೆ ಕಾರಣವಾಗಬಲ್ಲವು. ಈ ಎರಡೂ ಮಾರ್ಗಗಳಲ್ಲಿನ ಮೌಲ್ಯವನ್ನು ಕಂಡುಕೊಳ್ಳುವವರು ನಿಜವಾದ ಸತ್ಯವನ್ನು ಅರಿತುಕೊಳ್ಳುತ್ತಾರೆ."
  }
}