{
    "reference": "Chapter 6, Verse 11",
    "meanings": {
        "sanskrit": "शुचौ स्थले स्थिरासनं कृत्वा न अतीव उन्नतं न अतीव नीचं निरन्तरं शिरःस्थिरं कुर्वीत।",
        "english": "Sit in a clean place on a steady seat, keeping the posture neither too high nor too low, with a straight back.",
        "hindi": "स्वच्छ स्थान पर स्थिर आसन पर बैठें, न बहुत ऊँचा न बहुत नीचा, सीधा कंधा रखें।",
        "gujarati": "સુચિત સ્થળે સ્થિર બેઠા, ન વધારે ઊંચો ન ઓછો, સીધી પીઠ રાખો।",
        "tamil": "சுத்தமான இடத்தில் நிலையான அமர்வில் உட்கொண்டு, மிக உயரமாகவோ அல்லது மிகக் குறைவாகவோ இல்லாமல், நேராக உட்காரவும்।",
        "telugu": "శుభ్రమైన స్థలంలో స్థిరమైన కూర్చుని, చాలా ఎత్తుగా లేదా చాలా తక్కువగా కాకుండా, నిటారుగా కూర్చోండి।",
        "kannada": "ಶುಚಿತ ಸ್ಥಳದಲ್ಲಿ ಸ್ಥಿರ ಆಸನದಲ್ಲಿ ಕುಳಿತು, ಹೆಚ್ಚು ಎತ್ತರವಾಗಿಯೂ ಕಡಿಮೆ ಆಗಿಯೂ ಇಲ್ಲದೆ, ನೇರವಾಗಿ ಕುಳಿತುಕೊಳ್ಳಿ।"
    }
}