{
  "speaker": "",
  "reference": "Chapter 6, Verse 6.18",
  "sanskrit": "",
  "meanings": {
    "english": "Discipline helps you focus on what truly matters, letting go of selfish desires. This inner balance brings freedom from worldly cravings.",
    "hindi": "अनुशासन आपको वास्तव में महत्वपूर्ण बातों पर ध्यान केंद्रित करने में मदद करता है, स्वार्थी इच्छाओं को त्यागने देता है। यह आंतरिक संतुलन सांसारिक लालसाओं से मुक्ति लाता है।",
    "gujarati": "અંદરની શાંતિ અને સમતોલન એ વિશ્વના મોહથી મુક્તિ આપે છે. સંયમ તમને સાચા ધ્યેય પર ધ્યાન કેન્દ્રિત કરવામાં મદદ કરે છે, સ્વાર્થી ઇચ્છાઓનો ત્યાગ કરીને. આ અંદરનું સમતોલન વૈશ્વિક વાસનાઓથી મુક્તિ લાવે છે.",
    "tamil": "கட்டுப்பாடு உங்களை உண்மையில் முக்கியமானவற்றில் கவனம் செலுத்த உதவுகிறது, சுயநலம் கொண்ட விருப்பங்களை விட்டுவிட அனுமதிக்கிறது. இந்த உள்ளார்ந்த சமநிலை உலகியல் ஆசைகளில் இருந்து விடுதலையைக் கொடுக்கிறது.",
    "telugu": "నియమాలు మనసును నిజమైన విషయాలపై దృష్టి పెట్టడానికి సహాయపడతాయి, స్వార్థపూరిత కోరికలను వదిలివేయడానికి. ఈ అంతర్గత సమతౌల్యం లౌకిక వాంఛల నుండి విముక్తిని తెస్తుంది.",
    "kannada": "ನಿಯಮಗಳು ನಿಮಗೆ ನಿಜವಾಗಿ ಪ್ರಾಮುಖ್ಯವಾದವುಗಳ ಮೇಲೆ ಗಮನ ಕೇಂದ್ರೀಕರಿಸಲು ಸಹಾಯ ಮಾಡುತ್ತವೆ, ಸ್ವಾರ್ಥದ ಕಾಮನೆಗಳನ್ನು ತ್ಯಜಿಸುತ್ತವೆ. ಈ ಆಂತರಿಕ ಸಮತೋಲನವು ಲೌಕಿಕ ವಾಂಛೆಗಳಿಂದ ಮುಕ್ತಿಯನ್ನು ತರುತ್ತದೆ."
  }
}