{
    "reference": "Chapter 6, Verse 21",
    "meanings": {
        "sanskrit": "सच्चिदानन्दस्य निकटता, बौद्धिकग्राह्यं, इन्द्रियातीतं, आत्मा कत्रिचित् ज्ञात्वा, सत्यानन्दे स्थिरः न चलति।",
        "english": "One who knows that true happiness is near, is grasped by the intellect, beyond the senses, and who knows where the Self is, remains steady and unmoving in reality.",
        "hindi": "जो सच्ची खुशी के निकट है, उसे बुद्धि समझती है, इन्द्रियों से परे है, और आत्मा कहाँ है जानता है, वह सत्य में स्थिर रहता है और नहीं हिलता।",
        "gujarati": "જે સાચી ખુશી નજીક છે, તેને બુદ્ધિ સમજાવે છે, ઇન્દ્રિયોથી ઉપર છે, અને આત્મા કયા છે જાણે છે, તે સત્યમાં સ્થિર રહે છે અને ન હલે.",
        "tamil": "சத்தியமான மகிழ்ச்சி அருகில் உள்ளது, அது அறிவால் புரிந்துகொள்ளப்படுகிறது, உணர்வுகளுக்கு அப்பாற்பட்டது, ஆன்மா எங்கு உள்ளது என்று அறிந்தவர், உண்மையில் நிலைநிறுத்தப்பட்டு அசையாது.",
        "telugu": "నిజమైన సుఖం సమీపంలో ఉంది, అది బుద్ధి ద్వారా గ్రహించబడుతుంది, ఇంద్రియాలకు మించి ఉంటుంది, ఆత్మ ఎక్కడ ఉందో తెలుసుకునే వ్యక్తి, సత్యంలో స్థిరంగా ఉండి కదలడు.",
        "kannada": "ನಿಜವಾದ ಸಂತೋಷ ಸಮೀಪದಲ್ಲಿದೆ, ಅದು ಬುದ್ಧಿಯಿಂದ ಗ್ರಹಿಸಿಕೊಳ್ಳುತ್ತದೆ, ಇಂದ್ರಿಯಗಳಿಗಿಂತ ಮೇಲಾಗಿರುತ್ತದೆ, ಆತ್ಮ ಎಲ್ಲಿ ಇದೆ ಎಂದು ತಿಳಿದವನು, ಸತ್ಯದಲ್ಲಿ ಸ್ಥಿರವಾಗಿ ಅಚಲವಾಗಿರುತ್ತಾನೆ."
    }
}