{
  "speaker": "",
  "reference": "Chapter 6, Verse 6.23",
  "sanskrit": "",
  "meanings": {
    "english": "Detaching from pain and suffering is the goal of yoga. It requires unwavering dedication and a positive mindset.",
    "hindi": "दुःख और क्लेश से विमुख होना ही योग का उद्देश्य है। इसके लिए दृढ़ संकल्प और सकारात्मक दृष्टिकोण की आवश्यकता होती है।",
    "gujarati": "યોગનું લક્ષ્ય દુઃખ અને કષ્ટમાંથી નિર્લેપ થવાનું છે. તેમાં અડગ સમર્પણ અને સકારાત્મક દૃષ્ટિકોણની જરૂર પડે છે.",
    "tamil": "துன்பமும் துக்கமும் அகற்றுவதே யோகத்தின் குறிக்கோள். இதற்கு அசையாத அர்ப்பணிப்பும் நல்ல மனப்பான்மையும் தேவை.",
    "telugu": "యోగం యొక్క లక్ష్యం బాధ, దుఃఖాల నుండి విడుదల కావడం. ఇందుకు అలాంటి మనస్సు, అంకితభావం అవసరం.",
    "kannada": "ಯೋಗದ ಗುರಿ ವೇದನೆ ಮತ್ತು ಕಷ್ಟದಿಂದ ಬೇರ್ಪಡುವುದು. ಇದಕ್ಕೆ ಅತ್ಯಂತ ದೃಢವಾದ ನಿಷ್ಠೆ ಮತ್ತು ಸಕಾರಾತ್ಮಕ ಮನೋಭಾವ ಅಗತ್ಯವಿದೆ."
  }
}