{
  "speaker": "",
  "reference": "Chapter 7, Verse 7.29",
  "sanskrit": "",
  "meanings": {
    "english": "Those who seek freedom from suffering find inner peace and understanding. This understanding brings clarity to their actions and their true nature.",
    "hindi": "दुःख से मुक्ति पाने वाले लोग अंतरात्मिक शांति और समझ प्राप्त करते हैं। यह समझ उनके कार्यों और उनके वास्तविक स्वरूप को स्पष्टता प्रदान करती है।",
    "gujarati": "દુઃખથી મુક્તિ ઈચ્છતાઓ આંતરિક શાંતિ અને સમજણ મેળવે છે. આ સમજણ તેમના કૃત્યો અને તેમના વાસ્તવિક સ્વરૂપને સ્પષ્ટતા આપે છે.",
    "tamil": "துன்பத்திலிருந்து விடுதலை தேடுபவர்கள் உள்ளார்ந்த அமைதியையும் புரிதலையும் காண்கிறார்கள். இந்தப் புரிதல் அவர்களின் செயல்களுக்கும் அவர்களின் உண்மையான தன்மைக்கும் தெளிவைக் கொடுக்கிறது.",
    "telugu": "దుఃఖము నుండి విముక్తిని కోరేవారు ఆంతరిక శాంతిని, అవగాహనను పొందుతారు. ఈ అవగాహన వారి చర్యలకు, వారి నిజస్వరూపానికి స్పష్టతను కలిగిస్తుంది.",
    "kannada": "ದುಃಖದಿಂದ ಮುಕ್ತಿ ಪಡೆಯಲು ಬಯಸುವವರು ಆಂತರಿಕ ಶಾಂತಿ ಮತ್ತು ತಿಳುವಳಿಕೆಯನ್ನು ಪಡೆಯುತ್ತಾರೆ. ಈ ತಿಳುವಳಿಕೆಯು ಅವರ ಕ್ರಿಯೆಗಳಿಗೆ ಮತ್ತು ಅವರ ನಿಜವಾದ ಸ್ವರೂಪಕ್ಕೆ ಸ್ಪಷ್ಟತೆಯನ್ನು ತರುತ್ತದೆ."
  }
}