{
  "speaker": "",
  "reference": "Chapter 8, Verse 8.23 – 8.26",
  "sanskrit": "",
  "meanings": {
    "english": "There are two paths in life: one leads to spiritual liberation, while the other leads to rebirth. The path we choose determines our ultimate destination.",
    "hindi": "जीवन में दो मार्ग हैं: एक आत्मिक मुक्ति की ओर ले जाता है, जबकि दूसरा पुनर्जन्म की ओर ले जाता है। हम जिस मार्ग का चयन करते हैं, वह हमारे अंतिम गंतव्य का निर्धारण करता है।",
    "gujarati": "જીવનમાં બે માર્ગો છે: એક આધ્યાત્મિક મુક્તિ તરફ દોરી જાય છે, જ્યારે બીજો પુનર્જન્મ તરફ દોરી જાય છે. આપણે જે માર્ગ પસંદ કરીએ છીએ તે આપણા અંતિમ ગંતવ્ય નક્કી કરે છે.",
    "tamil": "இரண்டு பாதைகள் உள்ளன: ஒன்று ஆன்மீக விடுதலைக்கு வழிவகுக்கிறது, மற்றொன்று மறுபிறப்புக்கு வழிவகுக்கிறது. நாம் தேர்ந்தெடுக்கும் பாதை எங்கள் இறுதி சேருமிடத்தை நிர்ணயிக்கிறது.",
    "telugu": "జీవితంలో రెండు మార్గాలున్నాయి: ఒకటి ఆధ్యాత్మిక విముక్తికి దారితీస్తుంది, మరొకటి పునర్జన్మకు దారితీస్తుంది. మనం ఎంచుకున్న మార్గం మన తుది గమ్యాన్ని నిర్ణయిస్తుంది.",
    "kannada": "ಜೀವನದಲ್ಲಿ ಎರಡು ಮಾರ್ಗಗಳಿವೆ: ಒಂದು ಆಧ್ಯಾತ್ಮಿಕ ಮೋಕ್ಷಕ್ಕೆ ಕರೆದೊಯ್ಯುತ್ತದೆ, ಮತ್ತೊಂದು ಪುನರ್ಜನ್ಮಕ್ಕೆ ಕರೆದೊಯ್ಯುತ್ತದೆ. ನಾವು ಆಯ್ಕೆ ಮಾಡುವ ಮಾರ್ಗವು ನಮ್ಮ ಅಂತಿಮ ತಾಣವನ್ನು ನಿರ್ಧರಿಸುತ್ತದೆ."
  }
}