{
    "reference": "Chapter 11, Verse 52",
    "meanings": {
        "sanskrit": "इदं अद्भुतं रूपं सर्वदेवाः निरन्तरं दृष्टुं इच्छन्ति।",
        "english": "This wondrous form of the Divine is so rare that even the gods constantly wish to behold it.",
        "hindi": "यह अद्भुत दिव्य रूप इतना दुर्लभ है कि देवता भी निरन्तर इसे देखना चाहते हैं।",
        "gujarati": "આ અદ્ભુત દિવ્ય રૂપ એટલું દુર્લભ છે કે દેવતાઓ પણ સતત તેને જોવા ઈચ્છે છે.",
        "tamil": "இந்த அற்புதமான தெய்வீக வடிவம் மிகவும் அரிதானது; தேவதூதர்களும் தொடர்ந்து அதை காண விரும்புகிறார்கள்.",
        "telugu": "ఈ అద్భుతమైన దైవ రూపం ఎంతో అరుదైనది; దేవతలు కూడా నిరంతరం దాన్ని చూడాలని కోరుకుంటారు.",
        "kannada": "ಈ ಅದ್ಭುತ ದೈವಿಕ ರೂಪವು ಅತ್ಯಂತ ಅಪರೂಪ; ದೇವರುಗಳೂ ನಿರಂತರವಾಗಿ ಅದನ್ನು ನೋಡುವ ಆಸೆ ಹೊಂದಿದ್ದಾರೆ."
    }
}