{
  "speaker": "",
  "reference": "Chapter 18, Verse 18.23",
  "sanskrit": "",
  "meanings": {
    "english": "Act selflessly, following the right path, without personal gain or emotional attachment. This leads to a higher, more virtuous state of being.",
    "hindi": "निष्काम भाव से कर्म करो, न्याय के मार्ग पर चलते हुए, व्यक्तिगत लाभ या भावनात्मक मोह के बिना। यह उच्च, अधिक नैतिक स्थिति की ओर ले जाता है।",
    "gujarati": "નિષ્કામ કર્મ કરો, સાચા માર્ગ પર ચાલો, વ્યક્તિગત લાભ અથવા ભાવનાત્મક જોડાણ વિના. આ ઉચ્ચ, ધાર્મિક અસ્તિત્વની સ્થિતિ તરફ દોરી જાય છે.",
    "tamil": "சுயநலமில்லாமல், நன்னெறி பின்பற்றி, சொந்த பயனை நோக்காமலும், உணர்வுப்பூர்வமான இணைப்பில்லாமலும் செயல்படு. இது ஒரு உயர்ந்த, நற்பண்புமிக்க நிலைக்கு வழிவகுக்கிறது.",
    "telugu": "స్వార్థం లేకుండా, వ్యామోహం లేకుండా, నిష్కామంగా ధర్మమార్గంలో నడిచినప్పుడు మనం ఉన్నతమైన, నైతికమైన స్థితిని పొందుతాం.",
    "kannada": "ಸ್ವಾರ್ಥ ಮತ್ತು ಭಾವನಾತ್ಮಕ ಆಸಕ್ತಿಯಿಲ್ಲದೆ, ಸರಿಯಾದ ಮಾರ್ಗವನ್ನು ಅನುಸರಿಸಿ ನಿಷ್ಕಾಮವಾಗಿ ಕೆಲಸ ಮಾಡಿ. ಇದು ಹೆಚ್ಚು ಉನ್ನತ ಮತ್ತು ನೀತಿಯುಕ್ತ ಅಸ್ತಿತ್ವಕ್ಕೆ ಕಾರಣವಾಗುತ್ತದೆ."
  }
}