{
  "speaker": "",
  "reference": "Chapter 3, Verse 3.9",
  "sanskrit": "",
  "meanings": {
    "english": "Do your work selflessly for a higher purpose, not for personal gain. By doing so, you'll find freedom from worldly attachments and fulfill your true potential.",
    "hindi": "निष्काम भाव से उच्च उद्देश्य के लिए कार्य करो, न कि व्यक्तिगत लाभ के लिए। ऐसा करने से आप सांसारिक मोह से मुक्ति पाएंगे और अपनी सच्ची क्षमता को पूरा करेंगे।",
    "gujarati": "નિષ્કામ ભાવે કર્મ કરો, ઉચ્ચ હેતુ માટે કરો, વ્યક્તિગત લાભ માટે નહીં. આમ કરવાથી તમે સંસારના મોહથી મુક્તિ મેળવીશું અને તમારી સાચી ક્ષમતા પૂર્ણ કરીશું.",
    "tamil": "உயர்ந்த நோக்கத்திற்காக சுயநலமற்ற முறையில் உங்கள் பணியைச் செய்யுங்கள், சொந்த இலாபத்திற்காக அல்ல. இப்படி செய்வதன் மூலம் நீங்கள் உலகியல் இணைப்புகளிலிருந்து விடுதலையைக் கண்டு, உங்கள் உண்மையான திறனை நிறைவேற்றுவீர்கள்.",
    "telugu": "స్వార్థం కోసం కాకుండా ఉన్నత ఉద్దేశ్యం కోసం నిస్వార్థంగా పని చేయండి. దీని వలన మీరు లౌకిక బంధాల నుండి విముక్తిని పొంది, మీ నిజమైన సామర్థ్యాన్ని నెరవేరుస్తారు.",
    "kannada": "ನಿಮ್ಮ ಕೆಲಸವನ್ನು ಸ್ವಾರ್ಥವಿಲ್ಲದೆ ಉನ್ನತ ಉದ್ದೇಶಕ್ಕಾಗಿ ಮಾಡಿ, ವೈಯಕ್ತಿಕ ಲಾಭಕ್ಕಾಗಿ ಅಲ್ಲ. ಹಾಗೆ ಮಾಡುವುದರಿಂದ ನೀವು ಲೌಕಿಕ ಆಸಕ್ತಿಗಳಿಂದ ಮುಕ್ತರಾಗಿ ನಿಮ್ಮ ನಿಜವಾದ ಸಾಮರ್ಥ್ಯವನ್ನು ಪೂರೈಸುತ್ತೀರಿ."
  }
}